{
  "project_info": {
    "project_number": "687434243745",
    "project_id": "mister-lapkins",
    "storage_bucket": "mister-lapkins.firebasestorage.app"
  },
  "client": [
    {
      "client_info": {
        "mobilesdk_app_id": "1:687434243745:android:9e45309d0789a809df9ae0",
        "android_client_info": {
          "package_name": "com.lisitsa.misterlapkins"
        }
      },
      "oauth_client": [
        {
          "client_id": "687434243745-q89t1jgu5va56h6u8ulmbp11hq2ap4jg.apps.googleusercontent.com",
          "client_type": 1,
          "android_info": {
            "package_name": "com.lisitsa.misterlapkins",
            "certificate_hash": "8018d3cb25d4b65eb0bdaaaa514d949fb26023d9"
          }
        },
        {
          "client_id": "687434243745-vkih3g2auc2pmnkbe9ah9td4dq6fnvgh.apps.googleusercontent.com",
          "client_type": 1,
          "android_info": {
            "package_name": "com.lisitsa.misterlapkins",
            "certificate_hash": "df1559dde36280a86dcccbe3831465ce48c7e4af"
          }
        },
        {
          "client_id": "687434243745-c0nef82ioav7824blm1vjojrqaudskas.apps.googleusercontent.com",
          "client_type": 3
        }
      ],
      "api_key": [
        {
          "current_key": "AIzaSyAX3LndYkfetIlFbDWMtn0mY21LGsf-VG8"
        }
      ],
      "services": {
        "appinvite_service": {
          "other_platform_oauth_client": [
            {
              "client_id": "687434243745-c0nef82ioav7824blm1vjojrqaudskas.apps.googleusercontent.com",
              "client_type": 3
            }
          ]
        }
      }
    }
  ],
  "configuration_version": "1"
}